roff/__init__.py
roff/__main__.py
roff/_images.py
roff/_util.py
roff/convert.py
roff/__cli__/__init__.py
roff/__cli__/convert.py
roff/__cli__/from_parser.py
roff/__cli__/template.py
roff/__cli__/tree.py
roff/__cli__/util.py
roff/__cli__/watch.py
roff/_markdown/__init__.py
roff/_markdown/command.py
roff/_markdown/front_matter.py
roff-0.8.0.data/data/man/man1/roff.1
roff-0.8.0.data/data/man/man5/roff.5
roff-0.8.0.dist-info/licenses/LICENSE
roff-0.8.0.dist-info/METADATA
roff-0.8.0.dist-info/WHEEL
roff-0.8.0.dist-info/entry_points.txt
roff-0.8.0.dist-info/top_level.txt
roff-0.8.0.dist-info/RECORD
