Metadata-Version: 2.4
Name: roff
Version: 0.8.0
Summary: python-based cli to convert markdown to the roff (man-pages) format
License-Expression: GPL-3.0-or-later
Project-URL: Organisation GitHub, https://github.com/utility-toolbox
Project-URL: Homepage, https://github.com/utility-toolbox/roff/
Project-URL: Bug Tracker, https://github.com/utility-toolbox/roff/issues
Classifier: Intended Audience :: Developers
Classifier: Natural Language :: English
Classifier: Operating System :: OS Independent
Classifier: Programming Language :: Python :: 3
Classifier: Programming Language :: Python :: 3 :: Only
Classifier: Programming Language :: Python :: 3.6
Classifier: Programming Language :: Python :: 3.7
Classifier: Programming Language :: Python :: 3.8
Classifier: Programming Language :: Python :: 3.9
Classifier: Programming Language :: Python :: 3.10
Classifier: Programming Language :: Python :: 3.11
Classifier: Programming Language :: Python :: 3.12
Classifier: Programming Language :: Python :: 3.13
Classifier: Programming Language :: Python :: 3.14
Classifier: Topic :: Utilities
Requires-Python: >3.6
License-File: LICENSE
Requires-Dist: markdown-it-py
Provides-Extra: front-matter
Requires-Dist: pyyaml; extra == "front-matter"
Provides-Extra: images
Requires-Dist: pillow; extra == "images"
Provides-Extra: images-svg
Requires-Dist: pillow; extra == "images-svg"
Requires-Dist: cairosvg; extra == "images-svg"
Provides-Extra: watch
Requires-Dist: pypager; extra == "watch"
Dynamic: license-file
